wormbase_parasite/__init__.py
wormbase_parasite/wormbase_client.py
wormbase_parasite/endpoint_groups/__init__.py
wormbase_parasite/endpoint_groups/comparative_genomics.py
wormbase_parasite/endpoint_groups/cross_references.py
wormbase_parasite/endpoint_groups/information.py
wormbase_parasite/endpoint_groups/lookup.py
wormbase_parasite/endpoint_groups/mapping.py
wormbase_parasite/endpoint_groups/ontology.py
wormbase_parasite/endpoint_groups/overlap.py
wormbase_parasite/endpoint_groups/sequence.py
wormbase_parasite/endpoint_groups/util.py
wormbase_parasite-0.5.0.dist-info/LICENSE
wormbase_parasite-0.5.0.dist-info/METADATA
wormbase_parasite-0.5.0.dist-info/WHEEL
wormbase_parasite-0.5.0.dist-info/top_level.txt
wormbase_parasite-0.5.0.dist-info/RECORD
