Metadata-Version: 2.1
Name: wormbase-parasite
Version: 0.5.0
Summary: An interface to the Wormbase REST API
Home-page: https://github.com/chris-maclean/PyWormbase
Author: Christopher Maclean
Author-email: christopher.j.maclean@gmail.com
License: UNKNOWN
Platform: UNKNOWN
Classifier: Programming Language :: Python :: 3
Classifier: License :: OSI Approved :: GNU General Public License v3 (GPLv3)
Classifier: Operating System :: OS Independent
